algosec_appviz/__init__.py
algosec_appviz/environment.py
algosec_appviz/main.py
algosec_appviz-0.1.0.dist-info/METADATA
algosec_appviz-0.1.0.dist-info/WHEEL
algosec_appviz-0.1.0.dist-info/licenses/LICENSE
algosec_appviz-0.1.0.dist-info/RECORD
