Metadata-Version: 2.4
Name: algosec_appviz
Version: 0.1.0
Summary: AlgoSec AppViz Library
License: LICENSE
License-File: LICENSE
Author: Bogdan Radu
Requires-Python: >=3.9.0
Classifier: License :: Other/Proprietary License
Classifier: Programming Language :: Python :: 3
Classifier: Programming Language :: Python :: 3.9
Classifier: Programming Language :: Python :: 3.10
Classifier: Programming Language :: Python :: 3.11
Classifier: Programming Language :: Python :: 3.12
Classifier: Programming Language :: Python :: 3.13
Classifier: Programming Language :: Python :: 3.14
Requires-Dist: mydict (==2.1.0)
Requires-Dist: python-dotenv (>1.0.0)
Project-URL: Documentation, https://github.com/bogdan-iot/algosec-appviz/blob/master/README.md
Project-URL: Repository, https://github.com/bogdan-iot/algosec-appviz
